hogwarts/__init__.py
hogwarts/_test_views.py
hogwarts/apps.py
hogwarts/magic_templates/__init__.py
hogwarts/magic_templates/gen_templates.py
hogwarts/magic_tests/__init__.py
hogwarts/magic_tests/constants.py
hogwarts/magic_tests/factory.py
hogwarts/magic_tests/template.py
hogwarts/magic_tests/testcase.py
hogwarts/magic_urls/__init__.py
hogwarts/magic_urls/auto_urls.py
hogwarts/magic_urls/base.py
hogwarts/magic_urls/decorators.py
hogwarts/magic_urls/gen_urls.py
hogwarts/magic_urls/utils.py
hogwarts/magic_views/__init__.py
hogwarts/magic_views/gen_imports.py
hogwarts/magic_views/gen_views.py
hogwarts/management/__init__.py
hogwarts/management/commands/__init__.py
hogwarts/management/commands/base.py
hogwarts/management/commands/genfactories.py
hogwarts/management/commands/gentemplates.py
hogwarts/management/commands/gentests.py
hogwarts/management/commands/genurls.py
hogwarts/management/commands/genviews.py
hogwarts/management/commands/scaffold.py
hogwarts/migrations/0001_initial.py
hogwarts/migrations/__init__.py
hogwarts/models.py
hogwarts/scaffold/create.html
hogwarts/scaffold/detail.html
hogwarts/scaffold/list.html
hogwarts/scaffold/update.html
hogwarts/tests/__init__.py
hogwarts/tests/template_tests/__init__.py
hogwarts/tests/template_tests/gen_templates_tests.py
hogwarts/tests/tests/__init__.py
hogwarts/tests/tests/factory_tests.py
hogwarts/tests/tests/template_tests.py
hogwarts/tests/tests/testcase_tests.py
hogwarts/tests/url_tests/__init__.py
hogwarts/tests/url_tests/autourls_tests.py
hogwarts/tests/url_tests/base_tests.py
hogwarts/tests/url_tests/genurls_tests.py
hogwarts/tests/url_tests/url_scanner_tests.py
hogwarts/tests/view_tests/__init__.py
hogwarts/tests/view_tests/gen_import_tests.py
hogwarts/tests/view_tests/genviews_tests.py
hogwarts/urls.py
hogwarts/utils.py
hogwarts/views.py
django_hogwarts-0.9.0.dist-info/METADATA
django_hogwarts-0.9.0.dist-info/WHEEL
django_hogwarts-0.9.0.dist-info/RECORD
