Metadata-Version: 2.1
Name: django-hogwarts
Version: 0.9.0
Summary: Django utilities for codegen and DX improvement
Home-page: https://github.com/adiletto64/django-hogwarts
Keywords: django,django-utils,codegen
Author: adiletto64
Author-email: adiletdj19@gmail.com
Requires-Python: >=3.9,<4.0
Classifier: Programming Language :: Python :: 3
Classifier: Programming Language :: Python :: 3.9
Classifier: Programming Language :: Python :: 3.10
Classifier: Programming Language :: Python :: 3.11
Classifier: Programming Language :: Python :: 3.12
Requires-Dist: Jinja2 (>=3.1.2,<4.0.0)
Requires-Dist: rich (>=13.5.2,<14.0.0)
Project-URL: Documentation, https://django-hogwarts.vercel.app/
Project-URL: Repository, https://github.com/adiletto64/django-hogwarts
